odoo/addons/survey_description/README.rst
odoo/addons/survey_description/__init__.py
odoo/addons/survey_description/__manifest__.py
odoo/addons/survey_description/i18n/it.po
odoo/addons/survey_description/i18n/survey_description.pot
odoo/addons/survey_description/readme/CONTRIBUTORS.rst
odoo/addons/survey_description/readme/CREDITS.rst
odoo/addons/survey_description/readme/DESCRIPTION.rst
odoo/addons/survey_description/readme/ROADMAP.rst
odoo/addons/survey_description/readme/USAGE.rst
odoo/addons/survey_description/static/description/icon.png
odoo/addons/survey_description/static/description/icon.svg
odoo/addons/survey_description/static/description/index.html
odoo/addons/survey_description/views/survey_views.xml
odoo14_addon_survey_description-14.0.1.0.1.dev4.dist-info/METADATA
odoo14_addon_survey_description-14.0.1.0.1.dev4.dist-info/WHEEL
odoo14_addon_survey_description-14.0.1.0.1.dev4.dist-info/top_level.txt
odoo14_addon_survey_description-14.0.1.0.1.dev4.dist-info/RECORD
